cvbot/__init__.py
cvbot/_screen.py
cvbot/_sift.py
cvbot/ai.py
cvbot/capture.py
cvbot/colors.py
cvbot/images.py
cvbot/io.py
cvbot/keyboard.py
cvbot/match.py
cvbot/mouse.py
cvbot/nums.py
cvbot/strmatch.py
cvbot/test.py
cvbot/utils.py
cvbot/windows.py
cvbot/docs/source/conf.py
cvbot/yolo/ai.py
cvbot-3.1.7.dist-info/LICENSE
cvbot-3.1.7.dist-info/METADATA
cvbot-3.1.7.dist-info/WHEEL
cvbot-3.1.7.dist-info/top_level.txt
cvbot-3.1.7.dist-info/RECORD
