Metadata-Version: 2.1
Name: cvbot
Version: 3.1.7
Summary: Visual based desktop automation toolbox. Supports mouse & keyboard control
Author: Hisham Moe
Author-email: Hisham Moe <runeste2018@gmail.com>
License: LICENSE
Project-URL: Homepage, https://github.com/Runeste3/cvbot
Project-URL: Issues, https://github.com/Runeste3/cvbot/issues
Classifier: Programming Language :: Python :: 3
Classifier: License :: OSI Approved :: MIT License
Classifier: Operating System :: OS Independent
Requires-Python: >=3.9
License-File: LICENSE
Requires-Dist: opencv-python
Requires-Dist: numpy
Requires-Dist: mss
Requires-Dist: pynput
Requires-Dist: pywin32
Requires-Dist: easyocr
Requires-Dist: thefuzz[speedup]
Requires-Dist: onnx
Requires-Dist: onnxruntime
